setup.py
opmath/opmath.py
opmath.egg-info/PKG-INFO
opmath.egg-info/SOURCES.txt
opmath.egg-info/dependency_links.txt
opmath.egg-info/top_level.txt