Metadata-Version: 2.1
Name: opmath
Version: 1
Summary: An awesome package that does something
Home-page: http://pypi.python.org/pypi/operations/
Author: leo89stgbrasil
Author-email: leo89stg@gmail.com
License: GNU
Platform: UNKNOWN
